gnuhealth/__init__.py
gnuhealth/action/__init__.py
gnuhealth/action/main.py
gnuhealth/bus.py
gnuhealth/client.py
gnuhealth/common/__init__.py
gnuhealth/common/button.py
gnuhealth/common/cellrendererbinary.py
gnuhealth/common/cellrendererbutton.py
gnuhealth/common/cellrendererclickablepixbuf.py
gnuhealth/common/cellrenderercombo.py
gnuhealth/common/cellrendererfloat.py
gnuhealth/common/cellrendererinteger.py
gnuhealth/common/cellrenderertext.py
gnuhealth/common/cellrenderertoggle.py
gnuhealth/common/common.py
gnuhealth/common/completion.py
gnuhealth/common/datetime_.py
gnuhealth/common/domain_inversion.py
gnuhealth/common/domain_parser.py
gnuhealth/common/entry_position.py
gnuhealth/common/environment.py
gnuhealth/common/focus.py
gnuhealth/common/htmltextbuffer.py
gnuhealth/common/number_entry.py
gnuhealth/common/popup_menu.py
gnuhealth/common/richtext.py
gnuhealth/common/selection.py
gnuhealth/common/timedelta.py
gnuhealth/common/underline.py
gnuhealth/common/widget_style.py
gnuhealth/config.py
gnuhealth/data/locale/bg/LC_MESSAGES/tryton.mo
gnuhealth/data/locale/bg/LC_MESSAGES/tryton.po
gnuhealth/data/locale/ca/LC_MESSAGES/tryton.mo
gnuhealth/data/locale/ca/LC_MESSAGES/tryton.po
gnuhealth/data/locale/cs/LC_MESSAGES/tryton.mo
gnuhealth/data/locale/cs/LC_MESSAGES/tryton.po
gnuhealth/data/locale/de/LC_MESSAGES/tryton.mo
gnuhealth/data/locale/de/LC_MESSAGES/tryton.po
gnuhealth/data/locale/es/LC_MESSAGES/tryton.mo
gnuhealth/data/locale/es/LC_MESSAGES/tryton.po
gnuhealth/data/locale/es_419/LC_MESSAGES/tryton.mo
gnuhealth/data/locale/es_419/LC_MESSAGES/tryton.po
gnuhealth/data/locale/et/LC_MESSAGES/tryton.mo
gnuhealth/data/locale/et/LC_MESSAGES/tryton.po
gnuhealth/data/locale/fa/LC_MESSAGES/tryton.mo
gnuhealth/data/locale/fa/LC_MESSAGES/tryton.po
gnuhealth/data/locale/fi/LC_MESSAGES/tryton.mo
gnuhealth/data/locale/fi/LC_MESSAGES/tryton.po
gnuhealth/data/locale/fr/LC_MESSAGES/tryton.mo
gnuhealth/data/locale/fr/LC_MESSAGES/tryton.po
gnuhealth_client-5.0.1.dist-info/METADATA
gnuhealth_client-5.0.1.dist-info/WHEEL
gnuhealth_client-5.0.1.dist-info/entry_points.txt
gnuhealth_client-5.0.1.dist-info/licenses/COPYING
gnuhealth_client-5.0.1.dist-info/licenses/LICENSE
gnuhealth_client-5.0.1.dist-info/licenses/LICENSES/CC-BY-SA-4.0.txt
gnuhealth_client-5.0.1.dist-info/licenses/LICENSES/CC0-1.0.txt
gnuhealth_client-5.0.1.dist-info/licenses/LICENSES/GPL-3.0-or-later.txt
gnuhealth_client-5.0.1.dist-info/RECORD
