Metadata-Version: 2.4
Name: gnuhealth-client
Version: 5.0.1
Summary: GTK client for the GNU Health Hospital Management System
License-Expression: GPL-3.0-or-later
License-File: COPYING
License-File: LICENSE
License-File: LICENSES/CC-BY-SA-4.0.txt
License-File: LICENSES/CC0-1.0.txt
License-File: LICENSES/GPL-3.0-or-later.txt
Keywords: health,hospital,HIS,eHealth,gnuhealth
Author: GNU Solidario
Author-email: health@gnusolidario.org
Maintainer: Luis Falcon
Maintainer-email: falcon@gnuhealth.org
Requires-Python: >=3.10,<3.15
Classifier: Development Status :: 5 - Production/Stable
Classifier: Environment :: X11 Applications :: GTK
Classifier: Framework :: Tryton
Classifier: Intended Audience :: End Users/Desktop
Classifier: Intended Audience :: Healthcare Industry
Classifier: Natural Language :: English
Classifier: Operating System :: OS Independent
Classifier: Programming Language :: Python :: 3
Classifier: Programming Language :: Python :: 3.10
Classifier: Programming Language :: Python :: 3.11
Classifier: Programming Language :: Python :: 3.12
Classifier: Programming Language :: Python :: 3.13
Classifier: Programming Language :: Python :: 3.14
Classifier: Topic :: Scientific/Engineering :: Bio-Informatics
Classifier: Topic :: Scientific/Engineering :: Medical Science Apps.
Provides-Extra: calendar
Provides-Extra: sound
Requires-Dist: GooCalendar (>=0.7) ; extra == "calendar"
Requires-Dist: PyGObject (>=3.19)
Requires-Dist: playsound ; extra == "sound"
Requires-Dist: pycairo
Requires-Dist: python-dateutil
Project-URL: Bug Tracker, https://codeberg.org/gnuhealth/his-client/issues
Project-URL: Documentation, https://docs.gnuhealth.org
Project-URL: Homepage, https://www.gnuhealth.org
Project-URL: Repository, https://codeberg.org/gnuhealth/his-client
